[
  {
    "isim": "Steve Jobs",
    "mesaj": "Selam Bill Nasılsın?",
    "resim": "steveJobs.jpg",
    "saat": "00:18 AM",
    "suskun": "hayir",
    "ses" : "",
    "tik": "cift"
  },
  {
    "isim": "Nikola Tesla",
    "mesaj": "1 saat önce aktifti.",
    "resim": "nikolaTesla.jpg",
    "saat": "05:52 PM",
    "suskun": "evet",
    "ses" : "",
    "tik": "tek"
  },
  {
    "isim": "Ada Lovelace",
    "mesaj": "Bir Ses Klibi Gönderdi.",
    "resim": "adaLovelace.jpg",
    "saat": "03:37 PM",
    "suskun": "hayir",
    "ses": "merhaba.mp3",
    "tik": "yok"
  }
]
